gutenberg2zim/.jsbeautifyrc
gutenberg2zim/__about__.py
gutenberg2zim/__init__.py
gutenberg2zim/__main__.py
gutenberg2zim/constants.py
gutenberg2zim/database.py
gutenberg2zim/download.py
gutenberg2zim/entrypoint.py
gutenberg2zim/export.py
gutenberg2zim/iso639.py
gutenberg2zim/l10n.py
gutenberg2zim/pg_archive_urls.py
gutenberg2zim/rdf.py
gutenberg2zim/s3.py
gutenberg2zim/shared.py
gutenberg2zim/utils.py
gutenberg2zim/zim.py
gutenberg2zim/templates/Home.html
gutenberg2zim/templates/author.html
gutenberg2zim/templates/base.html
gutenberg2zim/templates/book_infobox.html
gutenberg2zim/templates/bookshelf.html
gutenberg2zim/templates/bookshelf_home.html
gutenberg2zim/templates/cover_article.html
gutenberg2zim/templates/favicon.ico
gutenberg2zim/templates/favicon.png
gutenberg2zim/templates/css/grids-responsive-min.css
gutenberg2zim/templates/css/logo_2.png
gutenberg2zim/templates/css/pure-min.css
gutenberg2zim/templates/css/pure-skin-gutenberg.css
gutenberg2zim/templates/css/spinner.gif
gutenberg2zim/templates/css/style.css
gutenberg2zim/templates/datatables/.gitignore
gutenberg2zim/templates/datatables/datatables.min.css
gutenberg2zim/templates/datatables/datatables.min.js
gutenberg2zim/templates/fonts/Roboto-Black.ttf
gutenberg2zim/templates/fonts/Roboto-Bold.ttf
gutenberg2zim/templates/fonts/Roboto-Light.ttf
gutenberg2zim/templates/fonts/Roboto-Medium.ttf
gutenberg2zim/templates/fonts/Roboto-Regular.ttf
gutenberg2zim/templates/fonts/Roboto-Thin.ttf
gutenberg2zim/templates/fonts/RobotoCondensed-Bold.ttf
gutenberg2zim/templates/fonts/RobotoCondensed-Light.ttf
gutenberg2zim/templates/fonts/RobotoCondensed-Regular.ttf
gutenberg2zim/templates/fonts/font-awesome/css/font-awesome.css
gutenberg2zim/templates/fonts/font-awesome/fonts/FontAwesome.otf
gutenberg2zim/templates/fonts/font-awesome/fonts/fontawesome-webfont.eot
gutenberg2zim/templates/fonts/font-awesome/fonts/fontawesome-webfont.svg
gutenberg2zim/templates/fonts/font-awesome/fonts/fontawesome-webfont.ttf
gutenberg2zim-2.2.0.dist-info/METADATA
gutenberg2zim-2.2.0.dist-info/WHEEL
gutenberg2zim-2.2.0.dist-info/entry_points.txt
gutenberg2zim-2.2.0.dist-info/licenses/LICENSE
gutenberg2zim-2.2.0.dist-info/RECORD
