Metadata-Version: 2.4
Name: gutenberg2zim
Version: 2.2.0
Summary: Make ZIM file from Gutenberg books
Project-URL: Homepage, https://github.com/openzim/kolibri
Project-URL: Donate, https://www.kiwix.org/en/support-us/
Author-email: Kiwix <dev@kiwix.org>
License: GPL-3.0-or-later
License-File: LICENSE
Keywords: gutenberg,kiwix,offline,zim
Classifier: License :: OSI Approved :: GNU General Public License v3 or later (GPLv3+)
Classifier: Programming Language :: Python :: 3
Classifier: Programming Language :: Python :: 3.13
Requires-Python: <3.14,>=3.13
Requires-Dist: apsw==3.40.0.0
Requires-Dist: babel==2.11.0
Requires-Dist: backoff==2.2.1
Requires-Dist: beautifulsoup4==4.9.3
Requires-Dist: chardet==5.1.0
Requires-Dist: docopt==0.6.2
Requires-Dist: jinja2==3.1.2
Requires-Dist: kiwixstorage==0.8.3
Requires-Dist: lxml==5.3.1
Requires-Dist: path-py==12.5.0
Requires-Dist: peewee==3.17.9
Requires-Dist: pif==0.8.2
Requires-Dist: requests==2.31.0
Requires-Dist: schedule==1.1.0
Requires-Dist: types-peewee==3.17.9.20250401
Requires-Dist: zimscraperlib==5.1.1
Provides-Extra: check
Requires-Dist: pyright==1.1.398; extra == 'check'
Provides-Extra: dev
Requires-Dist: black==25.1.0; extra == 'dev'
Requires-Dist: coverage==7.3.0; extra == 'dev'
Requires-Dist: debugpy==1.6.7; extra == 'dev'
Requires-Dist: hatchling==1.18.0; extra == 'dev'
Requires-Dist: invoke==2.2.0; extra == 'dev'
Requires-Dist: ipdb==0.13.13; extra == 'dev'
Requires-Dist: ipython==8.14.0; extra == 'dev'
Requires-Dist: pre-commit==3.3.3; extra == 'dev'
Requires-Dist: pyright==1.1.398; extra == 'dev'
Requires-Dist: pytest==7.4.0; extra == 'dev'
Requires-Dist: ruff==0.11.3; extra == 'dev'
Provides-Extra: lint
Requires-Dist: black==25.1.0; extra == 'lint'
Requires-Dist: ruff==0.11.3; extra == 'lint'
Provides-Extra: scripts
Requires-Dist: invoke==2.2.0; extra == 'scripts'
Provides-Extra: test
Requires-Dist: coverage==7.3.0; extra == 'test'
Requires-Dist: pytest==7.4.0; extra == 'test'
